LICENSE.txt
MANIFEST.in
README.md
setup.cfg
setup.py
PyEmailTools/Email.py
PyEmailTools/Forger.py
PyEmailTools/GPG.py
PyEmailTools/ImapClient.py
PyEmailTools/PopClient.py
PyEmailTools/Reader.py
PyEmailTools/SmtpClient.py
PyEmailTools/__init__.py
PyEmailTools/__main__.py
PyEmailTools.egg-info/PKG-INFO
PyEmailTools.egg-info/SOURCES.txt
PyEmailTools.egg-info/dependency_links.txt
PyEmailTools.egg-info/entry_points.txt
PyEmailTools.egg-info/top_level.txt